README.md
setup.py
mcs_packages/__init__.py
mcs_packages/sqrt.py
mcs_packages/square.py
mcs_packages.egg-info/PKG-INFO
mcs_packages.egg-info/SOURCES.txt
mcs_packages.egg-info/dependency_links.txt
mcs_packages.egg-info/entry_points.txt
mcs_packages.egg-info/top_level.txt